codingclash2020/__init__.py
codingclash2020/supervisor.py
codingclash2020/container/__init__.py
codingclash2020/container/interfacer.py
codingclash2020/game/__init__.py
codingclash2020/game/constants.py
codingclash2020/game/helpers.py
codingclash2020/game/moderator.py
codingclash2020/game/robot_type.py
codingclash2020/game/team.py
codingclash2020/game/team_color.py
codingclash2020/game/robots/__init__.py
codingclash2020/game/robots/attackable.py
codingclash2020/game/robots/barracks.py
codingclash2020/game/robots/builder.py
codingclash2020/game/robots/grenader.py
codingclash2020/game/robots/gunner.py
codingclash2020/game/robots/hq.py
codingclash2020/game/robots/moveable.py
codingclash2020/game/robots/refinery.py
codingclash2020/game/robots/robot.py
codingclash2020/game/robots/sensed_robot.py
codingclash2020/game/robots/spawnable.py
codingclash2020/game/robots/stunnable.py
codingclash2020/game/robots/tank.py
codingclash2020/game/robots/turret.py
codingclash2020/game/robots/wall.py
codingclash2020-1.2.1.dist-info/LICENSE
codingclash2020-1.2.1.dist-info/METADATA
codingclash2020-1.2.1.dist-info/WHEEL
codingclash2020-1.2.1.dist-info/top_level.txt
codingclash2020-1.2.1.dist-info/RECORD
