Metadata-Version: 2.1
Name: codingclash2020
Version: 1.2.1
Summary: Pip package containing the engine for CodingClash2020
Home-page: https://github.com/CodingClash2020/codingclash2020
Author: Srikar Gouru
Author-email: srikarg89@gmail.com
License: MIT
Platform: UNKNOWN
